LICENSE
MANIFEST.in
README.md
pyproject.toml
setup.py
confygure/__init__.py
confygure.egg-info/PKG-INFO
confygure.egg-info/SOURCES.txt
confygure.egg-info/dependency_links.txt
confygure.egg-info/requires.txt
confygure.egg-info/top_level.txt