Metadata-Version: 2.1
Name: confygure
Version: 0.0.3
Summary: A simple YAML based configuration library for Python
Author-email: Lars Kiesow <lkiesow@uos.de>
License: MIT
Project-URL: Homepage, https://github.com/lkiesow/confygure
Project-URL: Repository, https://github.com/lkiesow/confygure
Requires-Python: >=3.9
License-File: LICENSE
